mayim/__init__.py
mayim/convert.py
mayim/decorator.py
mayim/exception.py
mayim/log.py
mayim/mayim.py
mayim/py.typed
mayim/registry.py
mayim/base/__init__.py
mayim/base/executor.py
mayim/base/hydrator.py
mayim/base/interface.py
mayim/base/query.py
mayim/extension/__init__.py
mayim/extension/quart_extension.py
mayim/extension/sanic_extension.py
mayim/extension/starlette_extension.py
mayim/extension/statistics.py
mayim/lazy/__init__.py
mayim/lazy/interface.py
mayim/sql/__init__.py
mayim/sql/executor.py
mayim/sql/query.py
mayim/sql/mysql/__init__.py
mayim/sql/mysql/executor.py
mayim/sql/mysql/interface.py
mayim/sql/mysql/query.py
mayim/sql/postgres/__init__.py
mayim/sql/postgres/executor.py
mayim/sql/postgres/interface.py
mayim/sql/postgres/query.py
mayim/sql/sqlite/__init__.py
mayim/sql/sqlite/executor.py
mayim/sql/sqlite/interface.py
mayim/sql/sqlite/query.py
mayim/transaction/__init__.py
mayim/transaction/connection_manager.py
mayim/transaction/coordinator.py
mayim/transaction/interfaces.py
mayim/transaction/savepoint.py
mayim-1.3.1.dist-info/licenses/LICENSE
mayim-1.3.1.dist-info/METADATA
mayim-1.3.1.dist-info/WHEEL
mayim-1.3.1.dist-info/top_level.txt
mayim-1.3.1.dist-info/RECORD
