Metadata-Version: 2.4
Name: mayim
Version: 1.3.1
Summary: The NOT ORM hydrator
License: MIT
Keywords: orm
Classifier: Development Status :: 4 - Beta
Classifier: Environment :: Web Environment
Classifier: License :: OSI Approved :: MIT License
Classifier: Programming Language :: Python :: 3.8
Classifier: Programming Language :: Python :: 3.9
Classifier: Programming Language :: Python :: 3.10
Classifier: Programming Language :: Python :: 3.11
Classifier: Programming Language :: Python :: 3.12
Classifier: Programming Language :: Python :: 3.13
License-File: LICENSE
Provides-Extra: docs
Requires-Dist: pydoc-markdown; extra == "docs"
Provides-Extra: test
Requires-Dist: coverage; extra == "test"
Requires-Dist: pytest; extra == "test"
Requires-Dist: pytest-cov; extra == "test"
Requires-Dist: pytest-asyncio; extra == "test"
Requires-Dist: tox; extra == "test"
Provides-Extra: dev
Requires-Dist: coverage; extra == "dev"
Requires-Dist: pytest; extra == "dev"
Requires-Dist: pytest-cov; extra == "dev"
Requires-Dist: pytest-asyncio; extra == "dev"
Requires-Dist: tox; extra == "dev"
Requires-Dist: black; extra == "dev"
Requires-Dist: flake8; extra == "dev"
Requires-Dist: isort; extra == "dev"
Requires-Dist: mypy; extra == "dev"
Provides-Extra: postgres
Requires-Dist: psycopg; extra == "postgres"
Requires-Dist: psycopg_pool; extra == "postgres"
Provides-Extra: mysql
Requires-Dist: asyncmy; extra == "mysql"
Provides-Extra: sqlite
Requires-Dist: aiosqlite; extra == "sqlite"
Dynamic: license-file
